sqloxide-0.1.56.dist-info/METADATA
sqloxide-0.1.56.dist-info/WHEEL
sqloxide-0.1.56.dist-info/licenses/LICENSE
sqloxide/__init__.py
sqloxide/sqloxide.cpython-312-x86_64-linux-gnu.so
sqloxide-0.1.56.dist-info/RECORD
